pynmeaparser/__init__.py
pynmeaparser-1.0.0.dist-info/LICENSE
pynmeaparser-1.0.0.dist-info/METADATA
pynmeaparser-1.0.0.dist-info/WHEEL
pynmeaparser-1.0.0.dist-info/top_level.txt
pynmeaparser-1.0.0.dist-info/RECORD
