Metadata-Version: 2.1
Name: pynmeaparser
Version: 1.0.0
Summary: A package to parse general form of NMEA sentences. It is not specific to just certain devices only.
Author-email: Ahmad Shahril <shah25392+pypi@gmail.com>
Project-URL: Homepage, https://github.com/shah253kt/pynmeaparser
Project-URL: Bug Tracker, https://github.com/shah253kt/pynmeaparser/issues
Classifier: Operating System :: OS Independent
Classifier: Programming Language :: Python :: 3
Classifier: License :: OSI Approved :: MIT License
Classifier: Intended Audience :: Developers
Classifier: Intended Audience :: Science/Research
Classifier: Topic :: Utilities
Classifier: Topic :: Software Development :: Libraries :: Python Modules
Classifier: Topic :: Scientific/Engineering :: GIS
Requires-Python: >=3.6
License-File: LICENSE
